{"type":"FeatureCollection","features":[{"type":"Feature","properties":{"VSG_Name":"VSG-1","Stream":"Mekong River","Country":"Cambodia","Pass_Number":140,"Lon":105.481,"Lat":12.011},"geometry":{"type":"Point","coordinates":[105.481,12.011]}},{"type":"Feature","properties":{"VSG_Name":"VSG-2","Stream":"Tonle Sap River","Country":"Cambodia","Pass_Number":1,"Lon":104.483,"Lat":12.515},"geometry":{"type":"Point","coordinates":[104.483,12.515]}},{"type":"Feature","properties":{"VSG_Name":"VSG-3","Stream":"Mekong River","Country":"Laos/Thailand","Pass_Number":179,"Lon":103.94,"Lat":18.337},"geometry":{"type":"Point","coordinates":[103.94,18.337]}},{"type":"Feature","properties":{"VSG_Name":"VSG-4","Stream":"Lemro River","Country":"Myanmar","Pass_Number":129,"Lon":93.333,"Lat":20.1},"geometry":{"type":"Point","coordinates":[93.333,20.1]}},{"type":"Feature","properties":{"VSG_Name":"VSG-5","Stream":"Chindwin River","Country":"Myanmar","Pass_Number":129,"Lon":94.532,"Lat":22.88},"geometry":{"type":"Point","coordinates":[94.532,22.88]}},{"type":"Feature","properties":{"VSG_Name":"VSG-6","Stream":"Thanlyin River","Country":"Myanmar","Pass_Number":27,"Lon":97.602,"Lat":16.685},"geometry":{"type":"Point","coordinates":[97.602,16.685]}},{"type":"Feature","properties":{"VSG_Name":"VSG-7","Stream":"Tanintharyi River","Country":"Myanmar","Pass_Number":103,"Lon":98.748,"Lat":12.341},"geometry":{"type":"Point","coordinates":[98.748,12.341]}},{"type":"Feature","properties":{"VSG_Name":"VSG-8","Stream":"Ayeyarwady River","Country":"Myanmar","Pass_Number":166,"Lon":95.233,"Lat":16.509},"geometry":{"type":"Point","coordinates":[95.233,16.509]}},{"type":"Feature","properties":{"VSG_Name":"VSG-9","Stream":"Chindwin River","Country":"Myanmar","Pass_Number":242,"Lon":94.776,"Lat":24.265},"geometry":{"type":"Point","coordinates":[94.776,24.265]}},{"type":"Feature","properties":{"VSG_Name":"VSG-10","Stream":"Ayeyarwady River","Country":"Myanmar","Pass_Number":205,"Lon":94.575,"Lat":16.201},"geometry":{"type":"Point","coordinates":[94.575,16.201]}},{"type":"Feature","properties":{"VSG_Name":"VSG-11","Stream":"Ayeyarwady River","Country":"Myanmar","Pass_Number":205,"Lon":94.61,"Lat":16.29},"geometry":{"type":"Point","coordinates":[94.61,16.29]}},{"type":"Feature","properties":{"VSG_Name":"VSG-12","Stream":"Ayeyarwady River","Country":"Myanmar","Pass_Number":205,"Lon":94.685,"Lat":16.478},"geometry":{"type":"Point","coordinates":[94.685,16.478]}},{"type":"Feature","properties":{"VSG_Name":"VSG-13","Stream":"Ayeyarwady River","Country":"Myanmar","Pass_Number":205,"Lon":95.389,"Lat":18.223},"geometry":{"type":"Point","coordinates":[95.389,18.223]}},{"type":"Feature","properties":{"VSG_Name":"VSG-14","Stream":"Ayeyarwady River","Country":"Myanmar","Pass_Number":242,"Lon":95.822,"Lat":21.911},"geometry":{"type":"Point","coordinates":[95.822,21.911]}},{"type":"Feature","properties":{"VSG_Name":"VSG-15","Stream":"Ayeyarwady River","Country":"Myanmar","Pass_Number":64,"Lon":97.234,"Lat":25.09},"geometry":{"type":"Point","coordinates":[97.234,25.09]}},{"type":"Feature","properties":{"VSG_Name":"VSG-16","Stream":"Ho Thuy Dien Thac Mo","Country":"Vietnam","Pass_Number":77,"Lon":107.071,"Lat":11.864},"geometry":{"type":"Point","coordinates":[107.071,11.864]}},{"type":"Feature","properties":{"VSG_Name":"VSG-17","Stream":"Ho Thuy Dien Thac Mo","Country":"Vietnam","Pass_Number":77,"Lon":107.111,"Lat":11.971},"geometry":{"type":"Point","coordinates":[107.111,11.971]}},{"type":"Feature","properties":{"VSG_Name":"VSG-18","Stream":"Da River","Country":"Vietnam","Pass_Number":216,"Lon":104.699,"Lat":21.049},"geometry":{"type":"Point","coordinates":[104.699,21.049]}},{"type":"Feature","properties":{"VSG_Name":"VSG-19","Stream":"Song Co Chien","Country":"Vietnam","Pass_Number":77,"Lon":106.368,"Lat":9.985},"geometry":{"type":"Point","coordinates":[106.368,9.985]}},{"type":"Feature","properties":{"VSG_Name":"VSG-20","Stream":"Song Co Chien","Country":"Vietnam","Pass_Number":77,"Lon":106.415,"Lat":10.114},"geometry":{"type":"Point","coordinates":[106.415,10.114]}},{"type":"Feature","properties":{"FID":20,"VSG_Name":"VSG-21","Stream":"Ho Phu Ninh","Country":"Vietnam","Pass_Number":77,"Lon":108.467,"Lat":15.489},"geometry":{"type":"Point","coordinates":[108.467,15.489]}},{"type":"Feature","properties":{"VSG_Name":"VSG-22","Stream":"Se San","Country":"Vietnam","Pass_Number":216,"Lon":107.551,"Lat":14.013},"geometry":{"type":"Point","coordinates":[107.551,14.013]}}]}